arcalive/__init__.py
arcalive-0.5.3.dist-info/METADATA
arcalive-0.5.3.dist-info/WHEEL
arcalive-0.5.3.dist-info/top_level.txt
arcalive-0.5.3.dist-info/RECORD
