Metadata-Version: 2.1
Name: arcalive
Version: 0.5.3
Summary: Arca.live API
Home-page: UNKNOWN
Author: gramedcart
License: MIT
Platform: UNKNOWN
Classifier: Programming Language :: Python :: 3
Classifier: License :: OSI Approved :: MIT License
Classifier: Operating System :: OS Independent
Requires-Dist: bs4
Requires-Dist: requests
